vgetpupil/__init__.py
vgetpupil/detector.py
vgetpupil/vget.py
vgetpupil-2.0.1.dist-info/LICENSE
vgetpupil-2.0.1.dist-info/METADATA
vgetpupil-2.0.1.dist-info/WHEEL
vgetpupil-2.0.1.dist-info/entry_points.txt
vgetpupil-2.0.1.dist-info/top_level.txt
vgetpupil-2.0.1.dist-info/RECORD
