Metadata-Version: 2.1
Name: vgetpupil
Version: 2.0.1
Summary: pupil positions generator program
Home-page: https://github.com/jtur044/vgetpupil.git
Author: Zaw Lin Tun
Author-email: zawlintun1511@gmail.com
License: Apache Software
Keywords: pupil positions generator program vgetpupil
Platform: UNKNOWN
Classifier: Programming Language :: Python :: 3
Classifier: License :: OSI Approved :: Apache Software License
Classifier: Operating System :: OS Independent
License-File: LICENSE
Requires-Dist: setuptools
Requires-Dist: opencv-python
Requires-Dist: pupil-detectors
